pycrate-0.7.10.data/scripts/pycrate_asn1compile.py
pycrate-0.7.10.data/scripts/pycrate_berdecode.py
pycrate-0.7.10.data/scripts/pycrate_certdecode.py
pycrate-0.7.10.data/scripts/pycrate_extnas_demo.py
pycrate-0.7.10.data/scripts/pycrate_gtp_type_info.py
pycrate-0.7.10.data/scripts/pycrate_map_op_info.py
pycrate-0.7.10.data/scripts/pycrate_showmedia.py
pycrate-0.7.10.data/scripts/pycrate_shownas.py
pycrate-0.7.10.dist-info/licenses/license.txt
pycrate_asn1c/__init__.py
pycrate_asn1c/asnobj.py
pycrate_asn1c/asnproc.py
pycrate_asn1c/dictobj.py
pycrate_asn1c/err.py
pycrate_asn1c/extractor.py
pycrate_asn1c/generator.py
pycrate_asn1c/glob.py
pycrate_asn1c/refobj.py
pycrate_asn1c/setobj.py
pycrate_asn1c/specdir.py
pycrate_asn1c/tokenizer.py
pycrate_asn1c/utils.py
pycrate_asn1dir/AESCCMGCM.py
pycrate_asn1dir/AsymKeyPkg.py
pycrate_asn1dir/AuthEnvData.py
pycrate_asn1dir/CAP.py
pycrate_asn1dir/CDR.py
pycrate_asn1dir/CMS2004.py
pycrate_asn1dir/CMSAes.py
pycrate_asn1dir/CMSAlgs.py
pycrate_asn1dir/CMSAndPKIX08.py
pycrate_asn1dir/CMSFirmWrap.py
pycrate_asn1dir/E1AP.py
pycrate_asn1dir/E2AP.py
pycrate_asn1dir/ERS.py
pycrate_asn1dir/ExtSecServices.py
pycrate_asn1dir/F1AP.py
pycrate_asn1dir/H225.py
pycrate_asn1dir/H235.py
pycrate_asn1dir/H245.py
pycrate_asn1dir/H248.py
pycrate_asn1dir/HNBAP.py
pycrate_asn1dir/ILP.py
pycrate_asn1dir/ITS.py
pycrate_asn1dir/ITS_CAM_2.py
pycrate_asn1dir/ITS_DENM_3.py
pycrate_asn1dir/ITS_IEEE1609_2.py
pycrate_asn1dir/ITS_IS.py
pycrate_asn1dir/ITS_VAM_3.py
pycrate_asn1dir/ITS_r1318.py
pycrate_asn1dir/Kerberos.py
pycrate_asn1dir/LDAP.py
pycrate_asn1dir/LI3GPP.py
pycrate_asn1dir/LIETSI.py
pycrate_asn1dir/LIX3GPP.py
pycrate_asn1dir/LPP.py
pycrate_asn1dir/LPPa.py
pycrate_asn1dir/LPPe.py
pycrate_asn1dir/M2AP.py
pycrate_asn1dir/M3AP.py
pycrate_asn1dir/MAP.py
pycrate_asn1dir/MAPv2.py
pycrate_asn1dir/NBAP.py
pycrate_asn1dir/NCBI.py
pycrate_asn1dir/NCBI_all.py
pycrate_asn1dir/NGAP.py
pycrate_asn1dir/NRPPa.py
pycrate_asn1dir/PCAP.py
pycrate_asn1dir/PKCS1.py
pycrate_asn1dir/PKIX1.py
pycrate_asn1dir/PKIXAlgo08.py
pycrate-0.7.10.dist-info/METADATA
pycrate-0.7.10.dist-info/WHEEL
pycrate-0.7.10.dist-info/top_level.txt
pycrate-0.7.10.dist-info/RECORD
