Metadata-Version: 2.4
Name: pycrate
Version: 0.7.10
Summary: A software suite to handle various data and protocol formats
Home-page: https://github.com/pycrate-org/pycrate/
Author: Benoit Michau
Author-email: michau.benoit@gmail.com
License: LGPL v2.1+
Keywords: protocol format ASN.1 CSN.1 compiler encoder decoder mobile core network Diameter NAS S1AP NGAP TCAP MAP GTP PFCP SCCP ISUP
License-File: license.txt
Provides-Extra: naslte
Requires-Dist: CryptoMobile; extra == "naslte"
Provides-Extra: nas5g
Requires-Dist: CryptoMobile; extra == "nas5g"
Provides-Extra: corenet
Requires-Dist: pysctp; extra == "corenet"
Requires-Dist: CryptoMobile; extra == "corenet"
Provides-Extra: diameter-dict
Requires-Dist: lxml; extra == "diameter-dict"
Provides-Extra: sedebugmux
Requires-Dist: crcmod; extra == "sedebugmux"
Dynamic: author
Dynamic: author-email
Dynamic: description
Dynamic: description-content-type
Dynamic: home-page
Dynamic: keywords
Dynamic: license
Dynamic: license-file
Dynamic: provides-extra
Dynamic: summary
